{
   "SchoolID": 1461,
   "SchoolName": "University of North Carolina- Chapel Hill",
   "SchoolLocation": "Southeast",
   "SchoolEnvironment": "Suburban",
   "SchoolSize": 20954,
   "StudentFacultyRatio": 21,
   "SchoolType": "Public",
   "AcceptanceRate": "24%",
   "NLP": {
      "Reputation": 4.03583,
      "Facilities": 3.78171,
      "Happiness": 3.73952,
      "Clubs": 3.73981,
      "Location": 3.70817,
      "Food": 3.22731,
      "Social": 3.58464,
      "Opportunites": 3.9327,
      "Safety": 3.86114,
      "Internet": 3.5542
   },
   "ApplicationName": [
      "Common App",
      "Coalition App"
   ],
   "Tuition": {
      "General": {
         "in-state": 7019,
         "out-state": 32602
      },
      "IncomeSpecific": {
         "low": 4155,
         "medium-low": 6164,
         "medium": 12447,
         "medium-high": 19008,
         "high": 23907
      }
   },
   "Test": {
      "ACT": {
         "ACTUpperBound": 33,
         "ACTLowerBound": 28
      },
      "SAT": {
         "SATUpperBound": 1460,
         "SATLowerBound": 1270
      }
   },
   "Major": {
      "Business": 20,
      "Communication": 6,
      "Computer Science": 25,
      "Biology": 20,
      "Psychology": 8,
      "Engineering": 68
   },
   "Image": {
      "Logo": "https://horizan-images.s3.us-east-2.amazonaws.com/University/SchoolLogos/University_of_North_Carolina-_Chapel_Hilllogo.png",
      "General": [
         "https://horizan-images.s3.us-east-2.amazonaws.com/University/University_image/University_of_North_Carolina-_Chapel_Hill2.jpg",
         "https://horizan-images.s3.us-east-2.amazonaws.com/University/University_image/University_of_North_Carolina-_Chapel_Hill3.jpg",
         "https://horizan-images.s3.us-east-2.amazonaws.com/University/University_image/University_of_North_Carolina-_Chapel_Hill1.png"
      ]
   }
}